LICENSE
MANIFEST.in
README
setup.py
django_url_reduce.egg-info/PKG-INFO
django_url_reduce.egg-info/SOURCES.txt
django_url_reduce.egg-info/dependency_links.txt
django_url_reduce.egg-info/top_level.txt
django_url_reduce.egg-info/zip-safe
urlreduce/__init__.py
urlreduce/admin.py
urlreduce/context_processors.py
urlreduce/middleware.py
urlreduce/models.py
urlreduce/urls.py
urlreduce/utils.py
urlreduce/views.py