Metadata-Version: 1.0
Name: django-url-reduce
Version: 0.1.3
Summary: A Django pluggable app that automatically generates and injects shortlinks into your webpages.
Home-page: https://github.com/octothorp/django-url-reduce
Author: Kieran Lynn
Author-email: kieran@octothorpstudio.com
License: Copyright (c) 2010 Kieran Lynn
